aiae/__init__.py
aiae/main.py
aiae/netzsch.py
aiae-1.0.9.dist-info/WHEEL
aiae-1.0.9.dist-info/METADATA
aiae-1.0.9.dist-info/RECORD
